make_pretty/__init__.py
make_pretty/cli.py
make_pretty-1.2.1.dist-info/METADATA
make_pretty-1.2.1.dist-info/WHEEL
make_pretty-1.2.1.dist-info/entry_points.txt
make_pretty-1.2.1.dist-info/top_level.txt
make_pretty-1.2.1.dist-info/RECORD
