Metadata-Version: 2.4
Name: make-pretty
Version: 1.2.1
Summary: A command-line tool to format Python files with isort and black
Requires-Python: >=3.7
Requires-Dist: isort>=5
Requires-Dist: black>=24
